MANIFEST.in
README.md
README.rst
setup.py
ttl.egg-info/PKG-INFO
ttl.egg-info/SOURCES.txt
ttl.egg-info/dependency_links.txt
ttl.egg-info/requires.txt
ttl.egg-info/top_level.txt
ttlsuite/__init__.py