Metadata-Version: 1.1
Name: ttl
Version: 0.1a1
Summary: TTL-suite - a Python toolkit for managing and annotating textual content
Home-page: https://github.com/letuananh/ttl-suite
Author: Le Tuan Anh
Author-email: tuananh.ke@gmail.com
License: MIT License
Keywords: nlp
Platform: any
Classifier: Programming Language :: Python
Classifier: Development Status :: 2 - Pre-Alpha
Classifier: License :: OSI Approved :: MIT License
Classifier: Environment :: Plugins
Classifier: Intended Audience :: Education
Classifier: Intended Audience :: Science/Research
Classifier: Intended Audience :: Information Technology
Classifier: Intended Audience :: Developers
Classifier: Operating System :: OS Independent
Classifier: Topic :: Text Processing
Classifier: Topic :: Text Processing :: Linguistic
Classifier: Topic :: Software Development :: Libraries :: Python Modules
